ControlPyEmb/__init__.py
ControlPyEmb/ctrl.py
ControlPyEmb/datasets.py
ControlPyEmb-0.0.6.dist-info/LICENSE
ControlPyEmb-0.0.6.dist-info/METADATA
ControlPyEmb-0.0.6.dist-info/WHEEL
ControlPyEmb-0.0.6.dist-info/top_level.txt
ControlPyEmb-0.0.6.dist-info/RECORD
