Metadata-Version: 2.1
Name: ControlPyEmb
Version: 0.0.6
Summary: This library provides implementations for control-based graph embedding methods and benchmarks
Author: Anwar Said
Author-email: <anwar.said@vanderbilt.edu>
Keywords: python,control,graph machine learning,graph embeddings
Classifier: Development Status :: 5 - Production/Stable
Classifier: Intended Audience :: Science/Research
Classifier: License :: OSI Approved :: MIT License
Classifier: Programming Language :: Python :: 3
Classifier: Topic :: Scientific/Engineering
License-File: LICENSE
Requires-Dist: networkx
Requires-Dist: sphinx-rtd-theme
Requires-Dist: controlpy
